{"indexes":[{"deduplicate":true,"fields":["founders[*]"],"id":"1513709","selectivityEstimate":1,"sparse":false,"type":"hash","unique":false}],"parameters":{"allowUserKeys":true,"cacheEnabled":false,"cid":"1371274","deleted":false,"globallyUniqueId":"h8CDB8EDFEF88/1371274","id":"1371274","indexes":[{"fields":["_key"],"id":"0","selectivityEstimate":1,"sparse":false,"type":"primary","unique":true},{"deduplicate":true,"fields":["founders[*]"],"id":"1513709","selectivityEstimate":1,"sparse":false,"type":"hash","unique":false}],"isSmart":false,"isSystem":false,"keyOptions":{"allowUserKeys":true,"lastValue":1371893,"type":"traditional"},"name":"newGroups","numberOfShards":1,"planId":"1371274","replicationFactor":1,"shardKeys":["_key"],"shards":{},"status":3,"type":2,"version":6,"waitForSync":false}}